{
  "basics": {
    "name": "Yuxiang Xiao",
    "email": "yuxiangxiao02 [AT] gmail [DOT] com",
    "Github": "https://github.com/Yuxiang-Xiao/",
    "LinkedIn": "https://www.linkedin.com/in/yuxiangxiao/"
},
  "education": [
    {
      "institution": "National University of Singapore",
      "location": "Singapore",
      "url": "https://www.nus.edu.sg/",
      "area": "Robotics",
      "studyType": "Master",
      "startDate": "2024-08-05",
      "endDate": "2025-12-31",
      "score": "10",
      "courses": ["Theory of Relativity"]
    },
    {
      "institution": "South China University of Technology",
      "location": "Guangdong, China",
      "url": "https://www.scut.edu.cn/",
      "area": "Robotic Engineering",
      "studyType": "Bachelor",
      "startDate": "2020-09-01",
      "endDate": "2024-07-31",
      "score": "10",
      "courses": ["Theory of Relativity"]
    }
  ],
  "skills": [
    {
      "name": "Physics",
      "level": "Master",
      "icon": "fa-solid fa-hashtag",
      "keywords": [
        "Quantum Mechanics",
        "Quantum Computing",
        "Quantum Information",
        "Quantum Cryptography",
        "Quantum Communication",
        "Quantum Teleportation"
      ]
    }
  ],
  "languages": [
    {
      "language": "Chinese",
      "fluency": "Native speaker",
      "icon": ""
    },
    {
      "language": "English",
      "fluency": "Fluent",
      "icon": ""
    }
  ],
  "interests": [
    {
      "name": "Physics",
      "icon": "fa-solid fa-tag",
      "keywords": [
        "Quantum Mechanics",
        "Quantum Computing",
        "Quantum Information",
        "Quantum Cryptography",
        "Quantum Communication",
        "Quantum Teleportation"
      ]
    }
  ]
}
